__init__.py
osESD.py
parameters.py
models/__init__.py
models/auto_osESD_Detector.py
models/osESD_Detector.py
models/osESD_Test.py
models/osESD_Transform.py
utils/__init__.py
utils/data_aug.py
utils/plotting_modules.py
utils/scores_module.py
osESD-1.1.6.dist-info/LICENSE
osESD-1.1.6.dist-info/METADATA
osESD-1.1.6.dist-info/WHEEL
osESD-1.1.6.dist-info/top_level.txt
osESD-1.1.6.dist-info/RECORD
