Metadata-Version: 2.1
Name: osESD
Version: 1.1.6
Summary: Anomaly detection algorithm for time series datasets
Author-email: Sungwoo Kim <iguv221@naver.com>
Classifier: Programming Language :: Python :: 3.8
Classifier: License :: OSI Approved :: MIT License
Classifier: Operating System :: OS Independent
Requires-Python: >=3.8
License-File: LICENSE
